uart.v


module UART(
    input clk, // The master clock for this module
    input resetq, // Synchronous reset, active low
    input rx, // Incoming serial line
    output tx, // Outgoing serial line
    input rd, // read strobe  -- used only to clear valid flag.
    input wr, // write strobe   
    output reg valid, // Indicates a new byte is available. clears on read.
    output busy, // Low when transmit line is idle.
    input [7:0] tx_data, // Byte to transmit
    output reg [7:0] rx_data, // *Most recent* byte received -- whether or not the last was collected.
    output reg error // reception error
    );
// you can override these on a per-port basis, looks like:
//  buart #(.BAUD(115200)) _youruart (.clk(clk)...etc);
// or
//  buart #(.CLOCK_DIVIDE(312)) _uart1 (...
// The latter might be better for designs with non-48MHz clocks. 
parameter BAUD = 115200;
parameter CLKFREQ = 24000000;   // frequency of incoming signal 'clk'
parameter CLOCK_DIVIDE = (CLKFREQ / (BAUD * 4)); // clock rate (48Mhz) / (baud rate (460800) * 4)
// will probably want to support at least down to 9600 baud, which will require a CLOCK_DIVIDE == 1250

localparam CDSIZE = $clog2(CLOCK_DIVIDE)+1; // one more to accomodate assumed signed arithmatic
reg [5:0] bytephase;
reg [CDSIZE-1:0] rxclkcounter; 
wire rxqtick = rxclkcounter == CLOCK_DIVIDE; // strobes high one clk every 1/4 bit time
wire rxrst = rx & (~|bytephase); // rx goes low with the beginning of the start bit. synchronous to system clk, not sample clk.
always @(posedge clk) rxclkcounter <= rxrst | rxqtick ? 1 : rxclkcounter + 1; // initially held in reset
// very important: idle rx line holds rxrst asserted,
// this goes on *until* the start edge is found.
// thus synchronising further sampling to that edge, rather than remaining in phase with however it was reset.

wire rxstop = bytephase == 6'd40; // 11th sample 'tick' would have been at 42.
wire nonstarter;
always @(posedge clk) bytephase <= rxstop|nonstarter ? 0 : rxqtick ? bytephase + 1 : bytephase;
wire sample = (bytephase[1:0] == 2'b10) & rxqtick; // one clk for each of ten bits
// note sample is false while rxrst is true.
assign nonstarter = (bytephase == 6'd2) & rx; // start bit should still be low when sample strobes first.
// if it isn't, then it will go back to a rxrst state.

// after this point, we have a sample strobe, a rxstop strobe
reg [9:0] capture; always @(posedge clk) capture <= sample ? {rx, capture[9:1]} : capture;
// note bits are sent least-significant first.
wire startbit = capture[0]; // valid when rxstop strobes, and until rxrst releases for the next byte.
wire stopbit = capture[9];
wire good = stopbit&~startbit; // valid when rxstop is asserted. stop bit should be 1, start bit should have been zero.
always @(posedge clk) 
begin
valid <= rd ? 1'b0 : rxstop & good ? 1'b1 : valid;
rx_data <= rxstop & good ? capture[8:1] : rx_data;
error <= nonstarter ? 1'b1 : rxstop ? ~good : error ;
end
// tx parts
reg [CDSIZE+1:0] txclkcounter; // note, two extra bits to accomodate a limit 4x as large.
wire txtick = txclkcounter == 4*CLOCK_DIVIDE; // ticks for a clk once every bit, not every quarter bit.
always @(posedge clk) txclkcounter <= txtick ? 1 : txclkcounter + 1;
// note txclkcounter never needs to be reset out-of-phase with itself.
reg [3:0] sentbits; 
wire done = sentbits == 4'd10; // eventually stays 'done'. Reset to zero again when wr strobes.
always @(posedge clk) sentbits <= txtick & ~done ? sentbits + 1 : wr ? 4'd0 : sentbits ;
reg [9:0] sender;
// wr strobe might come any clk, not synchronous to txtick. No real need to force txtick to be synchronous to it either.
always @(posedge clk) sender <= wr ? {tx_data, 1'b0, 1'b1} : txtick ? {1'b1, sender[9:1]} : sender;
assign tx = sender[0]; // wr loads this 1, because tranmission doesn't start until the next txtick, whenever it arrives.
assign busy = ~done;
endmodule

ram.v
`timescale 1 ns / 1 ns

module RAM(din, write_en, waddr, wclk, raddr, rclk, dout);
    parameter init_file = "init.hex";
    parameter addr_width = 8;
    parameter data_width = 8;
    input wire [addr_width-1:0] waddr, raddr;
    input wire [data_width-1:0] din;
    input wire write_en, wclk, rclk;
    output reg [data_width-1:0] dout;
    reg [data_width-1:0] mem [(1<<addr_width)-1:0];
    always @(posedge wclk) // Write memory.
    begin
        if (write_en)
            mem[waddr] <= din; // Using write address bus.
    end
    always @(posedge rclk) // Read memory.
    begin
        dout <= mem[raddr]; // Using read address bus.
    end

    initial
    begin
        $readmemh(init_file, mem);  
    end 
endmodule

stack.v
`timescale 1 ns / 1 ns

module STACK #(
  parameter DEPTH = 8,
  parameter WIDTH = 8)(
  input wire clk,
  output wire [WIDTH-1:0] rd,
  input wire we,
  input wire [1:0] delta,   //[1=pop,0=push|1=move]
  input wire [WIDTH-1:0] wd);
  localparam BITS = (WIDTH * DEPTH) - 1;
  
  wire move = delta[0];

  reg [WIDTH-1:0] head;
  reg [BITS:0] tail;
  wire [WIDTH-1:0] headN;
  wire [BITS:0] tailN;

  assign headN = we ? wd : tail[WIDTH-1:0];
  assign tailN = delta[1] ? {{WIDTH{1'b0}}, tail[BITS:WIDTH]} : {tail[BITS-WIDTH:0], head};
  //                                  pop                             push

  always @(posedge clk) begin
    if (we | move)
      head <= headN;
    if (move)
      tail <= tailN;
  end

  assign rd = head;

endmodule

tok (1).v
`timescale 1 ns / 1 ns
`define TABLE_WIDTH 8 

// ~ call to addr in A
// { push tc on C_stk for loops
// } pop C_stk to tc
// pop C_stk to tc if A != 0
// ( store tc in table, skip until )
// ) if executing, pop C_stk to tc

module TOK(
  input wire clk,
  input wire reset,
  output wire tx,
  input  wire rx
  );


  // uart
  wire uart_rd = uart_rx_valid & T == "'";
  wire uart_wr = !uart_tx_busy & T == "\"";
  wire uart_rx_valid;
  wire uart_tx_busy;
  wire [7:0] uart_rx_data;
  wire uart_error;
  wire uart_stall = T == "\"" & uart_tx_busy | T == "'" & !uart_rx_valid;

  // ram
  wire write_flag = T == "#";    
  wire [7:0] A_low = A[7:0];
  wire [7:0] T;

  // A_stk
  wire [15:0] S;
  reg [1:0] A_stk_delta;
  reg A_stk_write;

  always @* begin
    case({stall, |depth, T})
      {2'b0_0, "("}    : {A_stk_write, A_stk_delta} = {1'b0, 2'b11}; //pop
      {2'b0_0, "+"}    : {A_stk_write, A_stk_delta} = {1'b0, 2'b11}; //pop
      {2'b0_0, "!"}    : {A_stk_write, A_stk_delta} = {1'b0, 2'b11}; //pop
      {2'b0_0, "%"}    : {A_stk_write, A_stk_delta} = {1'b0, 2'b11}; //pop
      {2'b0_0, ")"}    : {A_stk_write, A_stk_delta} = {1'b0, 2'b11}; //pop
      {2'b0_0, "~"}    : {A_stk_write, A_stk_delta} = {1'b0, 2'b11}; //pop
      {2'b0_0, " "}    : {A_stk_write, A_stk_delta} = {1'b1, 2'b01}; //push
      {2'b0_0, "$"}    : {A_stk_write, A_stk_delta} = {1'b1, 2'b01}; //push
      default          : {A_stk_write, A_stk_delta} = {1'b0, 2'b00}; //hold 
      endcase
    end  

  // C_stk
  reg [1:0] C_stk_delta;
  reg C_stk_write;
  wire [7:0] c_stk_w = T=="~" ? tc_plus_1 : T=="{" ? tc : A[7:0];
  wire [7:0] c_stk_r;

  always @* begin
    case({stall, |depth, T})
      {2'b0_0, "?"}    : {C_stk_write, C_stk_delta} = {1'b0, 2'b11}; //pop (return)
      {2'b0_0, ")"}    : {C_stk_write, C_stk_delta} = {1'b0, 2'b11}; //pop (return)
      {2'b0_0, "}"}    : {C_stk_write, C_stk_delta} = {1'b0, 2'b11}; //pop (return)
      {2'b0_0, "~"}    : {C_stk_write, C_stk_delta} = {1'b1, 2'b01}; //push (call)
      {2'b0_0, "{"}    : {C_stk_write, C_stk_delta} = {1'b1, 2'b01}; //push (call)
      default          : {C_stk_write, C_stk_delta} = {1'b0, 2'b00}; //hold
      endcase
    end 

  // table
  reg [`TABLE_WIDTH-1:0] idx, idx_;
  reg search_clk; 
  reg stall, stall_;

  wire table_search = (T=="!" | T=="@" | T=="~" | T=="(")  ? 1'b1 : 1'b0; 
  wire table_write = (T=="!" | T=="(") ? 1'b1 : 1'b0;
  wire [15:0] table_rd;
  wire [15:0] key_rd; 
  wire found_slot  = stall & (table_write ? (key_rd == A) | (key_rd == 0) 
                                           : (key_rd == A) & (key_rd != 0));

  wire write_slot = (table_write && found_slot && stall) ? 1'b1 : 1'b0;
  wire [15:0] table_wr_data = T == "(" ? tc_plus_1 : S;

  always @* begin
    casez({search_clk, found_slot, table_search, uart_stall, stall})
      5'b?_?_1_0_0: {stall_, idx_} = {1'b1, A[`TABLE_WIDTH-1:0]}; //table stall
      5'b1_0_1_0_1: {stall_, idx_} = {stall, idx + 1'b1};         //table clash, inc
      5'b1_1_1_0_1: {stall_, idx_} = {1'b0, idx};                 //table un-stall      
      5'b?_?_?_1_0: {stall_, idx_} = {1'b1, idx};                 //uart stall
      5'b?_?_?_0_1: {stall_, idx_} = {1'b0, idx};                 //uart un-stall      
      default:      {stall_, idx_} = {stall, idx};                //no change
      endcase
    end 
       

  // core
  reg [7:0] tc, tc_;
  wire [7:0] tc_plus_1 = tc + 1;
  reg [15:0] A, A_;    

  // A
  always @* begin
    if(depth==0 & T=="(") A_ = S;
    else if(stall | depth_) A_ = A; 
    else begin
      case(T)
        "0","1","2","3","4","5","6","7","8","9" : A_ = (A << 4) | (T - "0");
        "A","B","C","D","E","F" : A_ = (A << 4) | (T - "7");
        "a","b","c","d","e","f","g","h","i","j","k","l","m"
        ,"n","o","p","q","r","s","t","u","v","w","x","y","z" : A_ = ((A<<5)^16'h1505)^T;
        " " : A_ = 16'h0; 
        "+" : A_ = A + S;
        "-" : A_ = S - A;
        "_" : A_ = ~A;
        "=" : A_ = A == S ? -1 : 0;
        "!", "%", "~" : A_ = S;
        "@" : A_ = table_rd;
        "'" : A_ = A << 8 | uart_rx_data;
        "\"": A_ = A >> 8;
        default: A_ = A;
      endcase
    end  
  end

  // depth
  reg [3:0] depth, depth_;
  always @* begin
    case({stall, |depth, T})
      {2'b0_0,"("}     : depth_ = depth+1;
      {2'b0_1,")"}     : depth_ = depth-1;
      default          : depth_ = depth;
      endcase
    end  

  // tc
  always @* begin
    casez({stall_, depth, T})
      13'b1_????_????????  : tc_ <= tc; 
      {1'b0, 4'h0, "~"}    : tc_ <= table_rd;
      {1'b0, 4'h0, ")"}    : tc_ <= c_stk_r;  
      {1'b0, 4'h0, "}"}    : tc_ <= c_stk_r; 
      {1'b0, 4'h0, "?"}    : tc_ <= A ? c_stk_r : tc_plus_1;      
      default              : tc_ <= tc_plus_1;    
      endcase 
    end


  // march  
  always @(posedge clk or negedge reset) begin
    if (!reset) begin
      A <= 0;
      tc <= -1; 
      search_clk <= 0;
      depth <= 0;
      stall <= 0;
      idx <= 0;
      end
    else begin
      A <= A_;
      tc <= tc_; 
      depth <= depth_;
      search_clk <= ~search_clk;
      stall <= stall_;
      idx <= idx_;
      end
    end    


RAM ram(
.din(A[7:0]),
.write_en(write_flag),
.waddr(A_low),
.wclk(clk),
.raddr(tc_),
.rclk(clk),
.dout(T)
);
defparam ram.addr_width = 8;
defparam ram.data_width = 8;
defparam ram.init_file = "init.hex";

STACK A_stk(
.clk(clk),
.rd(S),
.wd(A),
.we(A_stk_write),
.delta(A_stk_delta)
);
defparam A_stk.DEPTH = 8;
defparam A_stk.WIDTH = 16;

STACK C_stk(
.clk(clk),
.rd(c_stk_r),
.wd(c_stk_w),
.we(C_stk_write),
.delta(C_stk_delta)
);
defparam C_stk.DEPTH = 8;
defparam C_stk.WIDTH = 8;

RAM keys(
.din(A),
.write_en(write_slot),
.waddr(idx),
.wclk(clk),
.raddr(idx),
.rclk(clk),
.dout(key_rd)
);
defparam keys.addr_width = `TABLE_WIDTH;
defparam keys.data_width = 16;
defparam keys.init_file = "blank256.hex"; 

RAM vals(
.din(table_wr_data),
.write_en(write_slot),
.waddr(idx),
.wclk(clk),
.raddr(idx),
.rclk(clk),
.dout(table_rd)
);
defparam vals.addr_width = `TABLE_WIDTH;
defparam vals.data_width = 16;
defparam vals.init_file = "blank256.hex"; 

UART uart(
.clk(clk),
.resetq(reset),
.rx(rx),
.tx(tx),
.rd(uart_rd), 
.wr(uart_wr),
.valid(uart_rx_valid),
.busy(uart_tx_busy),
.tx_data(A_low),
.rx_data(uart_rx_data),
.error(uart_error)
);



endmodule

test.v
`timescale 1 ns / 1 ns

module test;

  /* Make a reset that pulses once. */
  reg reset = 0;
  initial begin
     $dumpfile("wave.vcd");
     $dumpvars(0,test);

     # 1  reset = 1;
     # 512 $finish;
  end

  /* Make a regular pulsing clock. */
  reg clk = 0;
  always #1 clk = !clk;

  wire tx, rx;
  TOK tok(clk, reset, tx, rx);

endmodule // test

wave.vcd
$date
	Thu Dec 31 12:30:30 2020
$end
$version
	Icarus Verilog
$end
$timescale
	1ns
$end
$scope module test $end
$var wire 1 ! rx $end
$var wire 1 " tx $end
$var reg 1 # clk $end
$var reg 1 $ reset $end
$scope module tok $end
$var wire 1 # clk $end
$var wire 1 % found_slot $end
$var wire 1 $ reset $end
$var wire 1 ! rx $end
$var wire 1 & uart_rd $end
$var wire 1 ' uart_stall $end
$var wire 1 ( uart_wr $end
$var wire 1 ) write_slot $end
$var wire 1 * write_flag $end
$var wire 1 + uart_tx_busy $end
$var wire 1 , uart_rx_valid $end
$var wire 8 - uart_rx_data [7:0] $end
$var wire 1 . uart_error $end
$var wire 1 " tx $end
$var wire 8 / tc_plus_1 [7:0] $end
$var wire 1 0 table_write $end
$var wire 16 1 table_wr_data [15:0] $end
$var wire 1 2 table_search $end
$var wire 16 3 table_rd [15:0] $end
$var wire 16 4 key_rd [15:0] $end
$var wire 8 5 c_stk_w [7:0] $end
$var wire 8 6 c_stk_r [7:0] $end
$var wire 8 7 T [7:0] $end
$var wire 16 8 S [15:0] $end
$var wire 8 9 A_low [7:0] $end
$var reg 16 : A [15:0] $end
$var reg 16 ; A_ [15:0] $end
$var reg 2 < A_stk_delta [1:0] $end
$var reg 1 = A_stk_write $end
$var reg 2 > C_stk_delta [1:0] $end
$var reg 1 ? C_stk_write $end
$var reg 4 @ depth [3:0] $end
$var reg 4 A depth_ [3:0] $end
$var reg 8 B idx [7:0] $end
$var reg 8 C idx_ [7:0] $end
$var reg 1 D search_clk $end
$var reg 1 E stall $end
$var reg 1 F stall_ $end
$var reg 8 G tc [7:0] $end
$var reg 8 H tc_ [7:0] $end
$scope module A_stk $end
$var wire 1 # clk $end
$var wire 2 I delta [1:0] $end
$var wire 16 J rd [15:0] $end
$var wire 16 K wd [15:0] $end
$var wire 1 = we $end
$var wire 128 L tailN [127:0] $end
$var wire 1 M move $end
$var wire 16 N headN [15:0] $end
$var reg 16 O head [15:0] $end
$var reg 128 P tail [127:0] $end
$upscope $end
$scope module C_stk $end
$var wire 1 # clk $end
$var wire 2 Q delta [1:0] $end
$var wire 8 R rd [7:0] $end
$var wire 8 S wd [7:0] $end
$var wire 1 ? we $end
$var wire 64 T tailN [63:0] $end
$var wire 1 U move $end
$var wire 8 V headN [7:0] $end
$var reg 8 W head [7:0] $end
$var reg 64 X tail [63:0] $end
$upscope $end
$scope module keys $end
$var wire 16 Y din [15:0] $end
$var wire 8 Z raddr [7:0] $end
$var wire 1 # rclk $end
$var wire 8 [ waddr [7:0] $end
$var wire 1 # wclk $end
$var wire 1 ) write_en $end
$var reg 16 \ dout [15:0] $end
$upscope $end
$scope module ram $end
$var wire 8 ] din [7:0] $end
$var wire 8 ^ raddr [7:0] $end
$var wire 1 # rclk $end
$var wire 8 _ waddr [7:0] $end
$var wire 1 # wclk $end
$var wire 1 * write_en $end
$var reg 8 ` dout [7:0] $end
$upscope $end
$scope module uart $end
$var wire 1 + busy $end
$var wire 1 # clk $end
$var wire 1 a good $end
$var wire 1 b nonstarter $end
$var wire 1 & rd $end
$var wire 1 $ resetq $end
$var wire 1 ! rx $end
$var wire 1 c rxrst $end
$var wire 1 d sample $end
$var wire 8 e tx_data [7:0] $end
$var wire 1 ( wr $end
$var wire 1 f txtick $end
$var wire 1 " tx $end
$var wire 1 g stopbit $end
$var wire 1 h startbit $end
$var wire 1 i rxstop $end
$var wire 1 j rxqtick $end
$var wire 1 k done $end
$var reg 6 l bytephase [5:0] $end
$var reg 10 m capture [9:0] $end
$var reg 1 . error $end
$var reg 8 n rx_data [7:0] $end
$var reg 7 o rxclkcounter [6:0] $end
$var reg 10 p sender [9:0] $end
$var reg 4 q sentbits [3:0] $end
$var reg 9 r txclkcounter [8:0] $end
$var reg 1 , valid $end
$upscope $end
$scope module vals $end
$var wire 16 s din [15:0] $end
$var wire 8 t raddr [7:0] $end
$var wire 1 # rclk $end
$var wire 8 u waddr [7:0] $end
$var wire 1 # wclk $end
$var wire 1 ) write_en $end
$var reg 16 v dout [15:0] $end
$upscope $end
$upscope $end
$upscope $end
$enddefinitions $end
#0
$dumpvars
bx v
b0 u
b0 t
bx s
bx r
bx q
bx p
bx o
bx n
bx m
bx l
xk
xj
xi
xh
xg
xf
b0 e
xd
xc
xb
xa
bx `
b0 _
b0 ^
b0 ]
bx \
b0 [
b0 Z
b0 Y
bx X
bx W
bx V
0U
bx T
bx S
bx R
b0 Q
bx P
bx O
bx N
0M
bx L
b0 K
bx J
b0 I
b0 H
b11111111 G
0F
0E
0D
b0 C
b0 B
b0 A
b0 @
0?
b0 >
0=
b0 <
b0 ;
b0 :
b0 9
bx 8
bx 7
bx 6
bx 5
bx 4
bx 3
x2
bx 1
x0
b0 /
x.
bx -
x,
x+
x*
0)
x(
x'
x&
0%
0$
0#
x"
z!
$end
#1
b1 H
b1 ^
00
02
0'
b0 V
1U
b0 5
b0 S
0(
0&
1?
b1 >
b1 Q
0*
b1111011 7
b1111011 `
b0 4
b0 \
b0 3
b0 v
1D
b1 /
b0 G
1#
1$
#2
0#
#3
b10 H
b10 ^
x'
bx V
0U
bx00000000 T
x&
b0xxxxxxxx ;
0?
b0 >
b0 Q
b0 6
b0 R
b0 W
b100111 7
b100111 `
0D
b10 /
b1 G
1#
#4
0#
#5
b11 H
b11 ^
bx 5
bx S
x(
0&
bx 9
bx _
bx e
bx ]
b0 ;
b100010 7
b100010 `
1D
b11 /
b10 G
b0xxxxxxxx :
b0xxxxxxxx K
b0xxxxxxxx Y
1#
#6
0#
#7
b0 H
b0 ^
b0xxxxxxxxxxxxxxxxxxxxxxxxxxxxxxxxxxxxxxxxxxxxxxxxxxxxxxxx T
b0 5
b0 S
0'
1U
0(
b11 >
b11 Q
b0 9
b0 _
b0 e
b0 ]
b1111101 7
b1111101 `
0D
b100 /
b11 G
b0 :
b0 K
b0 Y
1#
#8
0#
#9
b1 H
b1 ^
b0 V
bx T
1?
b1 >
b1 Q
b1111011 7
b1111011 `
b0xxxxxxxxxxxxxxxxxxxxxxxxxxxxxxxxxxxxxxxxxxxxxxxxxxxxxxxx X
bx 6
bx R
bx W
1D
b1 /
b0 G
1#
#10
0#
#11
b10 H
b10 ^
x'
bx V
0U
bx00000000 T
x&
b0xxxxxxxx ;
0?
b0 >
b0 Q
bx X
b0 6
b0 R
b0 W
b100111 7
b100111 `
0D
b10 /
b1 G
1#
#12
0#
#13
b11 H
b11 ^
bx 5
bx S
x(
0&
bx 9
bx _
bx e
bx ]
b0 ;
b100010 7
b100010 `
1D
b11 /
b10 G
b0xxxxxxxx :
b0xxxxxxxx K
b0xxxxxxxx Y
1#
#14
0#
#15
b0 H
b0 ^
b0xxxxxxxxxxxxxxxxxxxxxxxxxxxxxxxxxxxxxxxxxxxxxxxxxxxxxxxx T
b0 5
b0 S
0'
1U
0(
b11 >
b11 Q
b0 9
b0 _
b0 e
b0 ]
b1111101 7
b1111101 `
0D
b100 /
b11 G
b0 :
b0 K
b0 Y
1#
#16
0#
#17
b1 H
b1 ^
b0 V
bx T
1?
b1 >
b1 Q
b1111011 7
b1111011 `
b0xxxxxxxxxxxxxxxxxxxxxxxxxxxxxxxxxxxxxxxxxxxxxxxxxxxxxxxx X
bx 6
bx R
bx W
1D
b1 /
b0 G
1#
#18
0#
#19
b10 H
b10 ^
x'
bx V
0U
bx00000000 T
x&
b0xxxxxxxx ;
0?
b0 >
b0 Q
bx X
b0 6
b0 R
b0 W
b100111 7
b100111 `
0D
b10 /
b1 G
1#
#20
0#
#21
b11 H
b11 ^
bx 5
bx S
x(
0&
bx 9
bx _
bx e
bx ]
b0 ;
b100010 7
b100010 `
1D
b11 /
b10 G
b0xxxxxxxx :
b0xxxxxxxx K
b0xxxxxxxx Y
1#
#22
0#
#23
b0 H
b0 ^
b0xxxxxxxxxxxxxxxxxxxxxxxxxxxxxxxxxxxxxxxxxxxxxxxxxxxxxxxx T
b0 5
b0 S
0'
1U
0(
b11 >
b11 Q
b0 9
b0 _
b0 e
b0 ]
b1111101 7
b1111101 `
0D
b100 /
b11 G
b0 :
b0 K
b0 Y
1#
#24
0#
#25
b1 H
b1 ^
b0 V
bx T
1?
b1 >
b1 Q
b1111011 7
b1111011 `
b0xxxxxxxxxxxxxxxxxxxxxxxxxxxxxxxxxxxxxxxxxxxxxxxxxxxxxxxx X
bx 6
bx R
bx W
1D
b1 /
b0 G
1#
#26
0#
#27
b10 H
b10 ^
x'
bx V
0U
bx00000000 T
x&
b0xxxxxxxx ;
0?
b0 >
b0 Q
bx X
b0 6
b0 R
b0 W
b100111 7
b100111 `
0D
b10 /
b1 G
1#
#28
0#
#29
b11 H
b11 ^
bx 5
bx S
x(
0&
bx 9
bx _
bx e
bx ]
b0 ;
b100010 7
b100010 `
1D
b11 /
b10 G
b0xxxxxxxx :
b0xxxxxxxx K
b0xxxxxxxx Y
1#
#30
0#
#31
b0 H
b0 ^
b0xxxxxxxxxxxxxxxxxxxxxxxxxxxxxxxxxxxxxxxxxxxxxxxxxxxxxxxx T
b0 5
b0 S
0'
1U
0(
b11 >
b11 Q
b0 9
b0 _
b0 e
b0 ]
b1111101 7
b1111101 `
0D
b100 /
b11 G
b0 :
b0 K
b0 Y
1#
#32
0#
#33
b1 H
b1 ^
b0 V
bx T
1?
b1 >
b1 Q
b1111011 7
b1111011 `
b0xxxxxxxxxxxxxxxxxxxxxxxxxxxxxxxxxxxxxxxxxxxxxxxxxxxxxxxx X
bx 6
bx R
bx W
1D
b1 /
b0 G
1#
#34
0#
#35
b10 H
b10 ^
x'
bx V
0U
bx00000000 T
x&
b0xxxxxxxx ;
0?
b0 >
b0 Q
bx X
b0 6
b0 R
b0 W
b100111 7
b100111 `
0D
b10 /
b1 G
1#
#36
0#
#37
b11 H
b11 ^
bx 5
bx S
x(
0&
bx 9
bx _
bx e
bx ]
b0 ;
b100010 7
b100010 `
1D
b11 /
b10 G
b0xxxxxxxx :
b0xxxxxxxx K
b0xxxxxxxx Y
1#
#38
0#
#39
b0 H
b0 ^
b0xxxxxxxxxxxxxxxxxxxxxxxxxxxxxxxxxxxxxxxxxxxxxxxxxxxxxxxx T
b0 5
b0 S
0'
1U
0(
b11 >
b11 Q
b0 9
b0 _
b0 e
b0 ]
b1111101 7
b1111101 `
0D
b100 /
b11 G
b0 :
b0 K
b0 Y
1#
#40
0#
#41
b1 H
b1 ^
b0 V
bx T
1?
b1 >
b1 Q
b1111011 7
b1111011 `
b0xxxxxxxxxxxxxxxxxxxxxxxxxxxxxxxxxxxxxxxxxxxxxxxxxxxxxxxx X
bx 6
bx R
bx W
1D
b1 /
b0 G
1#
#42
0#
#43
b10 H
b10 ^
x'
bx V
0U
bx00000000 T
x&
b0xxxxxxxx ;
0?
b0 >
b0 Q
bx X
b0 6
b0 R
b0 W
b100111 7
b100111 `
0D
b10 /
b1 G
1#
#44
0#
#45
b11 H
b11 ^
bx 5
bx S
x(
0&
bx 9
bx _
bx e
bx ]
b0 ;
b100010 7
b100010 `
1D
b11 /
b10 G
b0xxxxxxxx :
b0xxxxxxxx K
b0xxxxxxxx Y
1#
#46
0#
#47
b0 H
b0 ^
b0xxxxxxxxxxxxxxxxxxxxxxxxxxxxxxxxxxxxxxxxxxxxxxxxxxxxxxxx T
b0 5
b0 S
0'
1U
0(
b11 >
b11 Q
b0 9
b0 _
b0 e
b0 ]
b1111101 7
b1111101 `
0D
b100 /
b11 G
b0 :
b0 K
b0 Y
1#
#48
0#
#49
b1 H
b1 ^
b0 V
bx T
1?
b1 >
b1 Q
b1111011 7
b1111011 `
b0xxxxxxxxxxxxxxxxxxxxxxxxxxxxxxxxxxxxxxxxxxxxxxxxxxxxxxxx X
bx 6
bx R
bx W
1D
b1 /
b0 G
1#
#50
0#
#51
b10 H
b10 ^
x'
bx V
0U
bx00000000 T
x&
b0xxxxxxxx ;
0?
b0 >
b0 Q
bx X
b0 6
b0 R
b0 W
b100111 7
b100111 `
0D
b10 /
b1 G
1#
#52
0#
#53
b11 H
b11 ^
bx 5
bx S
x(
0&
bx 9
bx _
bx e
bx ]
b0 ;
b100010 7
b100010 `
1D
b11 /
b10 G
b0xxxxxxxx :
b0xxxxxxxx K
b0xxxxxxxx Y
1#
#54
0#
#55
b0 H
b0 ^
b0xxxxxxxxxxxxxxxxxxxxxxxxxxxxxxxxxxxxxxxxxxxxxxxxxxxxxxxx T
b0 5
b0 S
0'
1U
0(
b11 >
b11 Q
b0 9
b0 _
b0 e
b0 ]
b1111101 7
b1111101 `
0D
b100 /
b11 G
b0 :
b0 K
b0 Y
1#
#56
0#
#57
b1 H
b1 ^
b0 V
bx T
1?
b1 >
b1 Q
b1111011 7
b1111011 `
b0xxxxxxxxxxxxxxxxxxxxxxxxxxxxxxxxxxxxxxxxxxxxxxxxxxxxxxxx X
bx 6
bx R
bx W
1D
b1 /
b0 G
1#
#58
0#
#59
b10 H
b10 ^
x'
bx V
0U
bx00000000 T
x&
b0xxxxxxxx ;
0?
b0 >
b0 Q
bx X
b0 6
b0 R
b0 W
b100111 7
b100111 `
0D
b10 /
b1 G
1#
#60
0#
#61
b11 H
b11 ^
bx 5
bx S
x(
0&
bx 9
bx _
bx e
bx ]
b0 ;
b100010 7
b100010 `
1D
b11 /
b10 G
b0xxxxxxxx :
b0xxxxxxxx K
b0xxxxxxxx Y
1#
#62
0#
#63
b0 H
b0 ^
b0xxxxxxxxxxxxxxxxxxxxxxxxxxxxxxxxxxxxxxxxxxxxxxxxxxxxxxxx T
b0 5
b0 S
0'
1U
0(
b11 >
b11 Q
b0 9
b0 _
b0 e
b0 ]
b1111101 7
b1111101 `
0D
b100 /
b11 G
b0 :
b0 K
b0 Y
1#
#64
0#
#65
b1 H
b1 ^
b0 V
bx T
1?
b1 >
b1 Q
b1111011 7
b1111011 `
b0xxxxxxxxxxxxxxxxxxxxxxxxxxxxxxxxxxxxxxxxxxxxxxxxxxxxxxxx X
bx 6
bx R
bx W
1D
b1 /
b0 G
1#
#66
0#
#67
b10 H
b10 ^
x'
bx V
0U
bx00000000 T
x&
b0xxxxxxxx ;
0?
b0 >
b0 Q
bx X
b0 6
b0 R
b0 W
b100111 7
b100111 `
0D
b10 /
b1 G
1#
#68
0#
#69
b11 H
b11 ^
bx 5
bx S
x(
0&
bx 9
bx _
bx e
bx ]
b0 ;
b100010 7
b100010 `
1D
b11 /
b10 G
b0xxxxxxxx :
b0xxxxxxxx K
b0xxxxxxxx Y
1#
#70
0#
#71
b0 H
b0 ^
b0xxxxxxxxxxxxxxxxxxxxxxxxxxxxxxxxxxxxxxxxxxxxxxxxxxxxxxxx T
b0 5
b0 S
0'
1U
0(
b11 >
b11 Q
b0 9
b0 _
b0 e
b0 ]
b1111101 7
b1111101 `
0D
b100 /
b11 G
b0 :
b0 K
b0 Y
1#
#72
0#
#73
b1 H
b1 ^
b0 V
bx T
1?
b1 >
b1 Q
b1111011 7
b1111011 `
b0xxxxxxxxxxxxxxxxxxxxxxxxxxxxxxxxxxxxxxxxxxxxxxxxxxxxxxxx X
bx 6
bx R
bx W
1D
b1 /
b0 G
1#
#74
0#
#75
b10 H
b10 ^
x'
bx V
0U
bx00000000 T
x&
b0xxxxxxxx ;
0?
b0 >
b0 Q
bx X
b0 6
b0 R
b0 W
b100111 7
b100111 `
0D
b10 /
b1 G
1#
#76
0#
#77
b11 H
b11 ^
bx 5
bx S
x(
0&
bx 9
bx _
bx e
bx ]
b0 ;
b100010 7
b100010 `
1D
b11 /
b10 G
b0xxxxxxxx :
b0xxxxxxxx K
b0xxxxxxxx Y
1#
#78
0#
#79
b0 H
b0 ^
b0xxxxxxxxxxxxxxxxxxxxxxxxxxxxxxxxxxxxxxxxxxxxxxxxxxxxxxxx T
b0 5
b0 S
0'
1U
0(
b11 >
b11 Q
b0 9
b0 _
b0 e
b0 ]
b1111101 7
b1111101 `
0D
b100 /
b11 G
b0 :
b0 K
b0 Y
1#
#80
0#
#81
b1 H
b1 ^
b0 V
bx T
1?
b1 >
b1 Q
b1111011 7
b1111011 `
b0xxxxxxxxxxxxxxxxxxxxxxxxxxxxxxxxxxxxxxxxxxxxxxxxxxxxxxxx X
bx 6
bx R
bx W
1D
b1 /
b0 G
1#
#82
0#
#83
b10 H
b10 ^
x'
bx V
0U
bx00000000 T
x&
b0xxxxxxxx ;
0?
b0 >
b0 Q
bx X
b0 6
b0 R
b0 W
b100111 7
b100111 `
0D
b10 /
b1 G
1#
#84
0#
#85
b11 H
b11 ^
bx 5
bx S
x(
0&
bx 9
bx _
bx e
bx ]
b0 ;
b100010 7
b100010 `
1D
b11 /
b10 G
b0xxxxxxxx :
b0xxxxxxxx K
b0xxxxxxxx Y
1#
#86
0#
#87
b0 H
b0 ^
b0xxxxxxxxxxxxxxxxxxxxxxxxxxxxxxxxxxxxxxxxxxxxxxxxxxxxxxxx T
b0 5
b0 S
0'
1U
0(
b11 >
b11 Q
b0 9
b0 _
b0 e
b0 ]
b1111101 7
b1111101 `
0D
b100 /
b11 G
b0 :
b0 K
b0 Y
1#
#88
0#
#89
b1 H
b1 ^
b0 V
bx T
1?
b1 >
b1 Q
b1111011 7
b1111011 `
b0xxxxxxxxxxxxxxxxxxxxxxxxxxxxxxxxxxxxxxxxxxxxxxxxxxxxxxxx X
bx 6
bx R
bx W
1D
b1 /
b0 G
1#
#90
0#
