uart.v


module UART(
    input clk, // The master clock for this module
    input resetq, // Synchronous reset, active low
    input rx, // Incoming serial line
    output tx, // Outgoing serial line
    input rd, // read strobe  -- used only to clear valid flag.
    input wr, // write strobe   
    output reg valid, // Indicates a new byte is available. clears on read.
    output busy, // Low when transmit line is idle.
    input [7:0] tx_data, // Byte to transmit
    output reg [7:0] rx_data, // *Most recent* byte received -- whether or not the last was collected.
    output reg error // reception error
    );
// you can override these on a per-port basis, looks like:
//  buart #(.BAUD(115200)) _youruart (.clk(clk)...etc);
// or
//  buart #(.CLOCK_DIVIDE(312)) _uart1 (...
// The latter might be better for designs with non-48MHz clocks. 
parameter BAUD = 115200;
parameter CLKFREQ = 24000000;   // frequency of incoming signal 'clk'
parameter CLOCK_DIVIDE = (CLKFREQ / (BAUD * 4)); // clock rate (48Mhz) / (baud rate (460800) * 4)
// will probably want to support at least down to 9600 baud, which will require a CLOCK_DIVIDE == 1250

localparam CDSIZE = $clog2(CLOCK_DIVIDE)+1; // one more to accomodate assumed signed arithmatic
reg [5:0] bytephase;
reg [CDSIZE-1:0] rxclkcounter; 
wire rxqtick = rxclkcounter == CLOCK_DIVIDE; // strobes high one clk every 1/4 bit time
wire rxrst = rx & (~|bytephase); // rx goes low with the beginning of the start bit. synchronous to system clk, not sample clk.
always @(posedge clk) rxclkcounter <= rxrst | rxqtick ? 1 : rxclkcounter + 1; // initially held in reset
// very important: idle rx line holds rxrst asserted,
// this goes on *until* the start edge is found.
// thus synchronising further sampling to that edge, rather than remaining in phase with however it was reset.

wire rxstop = bytephase == 6'd40; // 11th sample 'tick' would have been at 42.
wire nonstarter;
always @(posedge clk) bytephase <= rxstop|nonstarter ? 0 : rxqtick ? bytephase + 1 : bytephase;
wire sample = (bytephase[1:0] == 2'b10) & rxqtick; // one clk for each of ten bits
// note sample is false while rxrst is true.
assign nonstarter = (bytephase == 6'd2) & rx; // start bit should still be low when sample strobes first.
// if it isn't, then it will go back to a rxrst state.

// after this point, we have a sample strobe, a rxstop strobe
reg [9:0] capture; always @(posedge clk) capture <= sample ? {rx, capture[9:1]} : capture;
// note bits are sent least-significant first.
wire startbit = capture[0]; // valid when rxstop strobes, and until rxrst releases for the next byte.
wire stopbit = capture[9];
wire good = stopbit&~startbit; // valid when rxstop is asserted. stop bit should be 1, start bit should have been zero.
always @(posedge clk) 
begin
valid <= rd ? 1'b0 : rxstop & good ? 1'b1 : valid;
rx_data <= rxstop & good ? capture[8:1] : rx_data;
error <= nonstarter ? 1'b1 : rxstop ? ~good : error ;
end
// tx parts
reg [CDSIZE+1:0] txclkcounter; // note, two extra bits to accomodate a limit 4x as large.
wire txtick = txclkcounter == 4*CLOCK_DIVIDE; // ticks for a clk once every bit, not every quarter bit.
always @(posedge clk) txclkcounter <= txtick ? 1 : txclkcounter + 1;
// note txclkcounter never needs to be reset out-of-phase with itself.
reg [3:0] sentbits; 
wire done = sentbits == 4'd10; // eventually stays 'done'. Reset to zero again when wr strobes.
always @(posedge clk) sentbits <= txtick & ~done ? sentbits + 1 : wr ? 4'd0 : sentbits ;
reg [9:0] sender;
// wr strobe might come any clk, not synchronous to txtick. No real need to force txtick to be synchronous to it either.
always @(posedge clk) sender <= wr ? {tx_data, 1'b0, 1'b1} : txtick ? {1'b1, sender[9:1]} : sender;
assign tx = sender[0]; // wr loads this 1, because tranmission doesn't start until the next txtick, whenever it arrives.
assign busy = ~done;
endmodule

ram.v
`timescale 1 ns / 1 ns

module RAM(din, write_en, waddr, wclk, raddr, rclk, dout);
    parameter init_file = "init.hex";
    parameter addr_width = 8;
    parameter data_width = 8;
    input wire [addr_width-1:0] waddr, raddr;
    input wire [data_width-1:0] din;
    input wire write_en, wclk, rclk;
    output reg [data_width-1:0] dout;
    reg [data_width-1:0] mem [(1<<addr_width)-1:0];
    always @(posedge wclk) // Write memory.
    begin
        if (write_en)
            mem[waddr] <= din; // Using write address bus.
    end
    always @(posedge rclk) // Read memory.
    begin
        dout <= mem[raddr]; // Using read address bus.
    end

    initial
    begin
        $readmemh(init_file, mem);  
    end 
endmodule

stack.v
`timescale 1 ns / 1 ns

module STACK #(
  parameter DEPTH = 8,
  parameter WIDTH = 8)(
  input wire clk,
  output wire [WIDTH-1:0] rd,
  input wire we,
  input wire [1:0] delta,   //[1=pop,0=push|1=move]
  input wire [WIDTH-1:0] wd);
  localparam BITS = (WIDTH * DEPTH) - 1;
  
  wire move = delta[0];

  reg [WIDTH-1:0] head;
  reg [BITS:0] tail;
  wire [WIDTH-1:0] headN;
  wire [BITS:0] tailN;

  assign headN = we ? wd : tail[WIDTH-1:0];
  assign tailN = delta[1] ? {{WIDTH{1'b0}}, tail[BITS:WIDTH]} : {tail[BITS-WIDTH:0], head};
  //                                  pop                             push

  always @(posedge clk) begin
    if (we | move)
      head <= headN;
    if (move)
      tail <= tailN;
  end

  assign rd = head;

endmodule

tok.v
`timescale 1 ns / 1 ns
`define TABLE_WIDTH 8
`define RAM_WIDTH 8 

// ~ call to addr in A
// { push tc on C_stk for loops
// } pop C_stk to tc
// ? pop C_stk to tc if A != 0
// ( store tc in table, skip until )
// ) if executing, pop C_stk to tc

module TOK(
  input wire clk,
  input wire reset,
  output wire tx,
  input  wire rx
  );


  // uart
  wire uart_rd = uart_rx_valid & T == "'";
  wire uart_wr = !uart_tx_busy & T == "\"";
  wire uart_rx_valid;
  wire uart_tx_busy;
  wire [7:0] uart_rx_data;
  wire uart_error;
  wire uart_stall = (T == "\"" & uart_tx_busy) | (T == "'" & !uart_rx_valid);

  // ram
  wire write_flag = T == "#";    
  wire [7:0] A_low = A[7:0];
  wire [7:0] T;

  // A_stk
  wire [15:0] S;
  reg [1:0] A_stk_delta;
  reg A_stk_write;

  always @* begin
    case({stall, |depth, T})
      {2'b0_0, "("}    : {A_stk_write, A_stk_delta} = {1'b0, 2'b11}; //pop
      {2'b0_0, "+"}    : {A_stk_write, A_stk_delta} = {1'b0, 2'b11}; //pop
      {2'b0_0, "!"}    : {A_stk_write, A_stk_delta} = {1'b0, 2'b11}; //pop
      {2'b0_0, "%"}    : {A_stk_write, A_stk_delta} = {1'b0, 2'b11}; //pop
      {2'b0_0, ")"}    : {A_stk_write, A_stk_delta} = {1'b0, 2'b11}; //pop
      {2'b0_0, "~"}    : {A_stk_write, A_stk_delta} = {1'b0, 2'b11}; //pop
      {2'b0_0, "#"}    : {A_stk_write, A_stk_delta} = {1'b0, 2'b11}; //pop
      {2'b0_0, " "}    : {A_stk_write, A_stk_delta} = {1'b1, 2'b01}; //push
      {2'b0_0, "$"}    : {A_stk_write, A_stk_delta} = {1'b1, 2'b01}; //push
      default          : {A_stk_write, A_stk_delta} = {1'b0, 2'b00}; //hold 
      endcase
    end  

  // C_stk
  reg [1:0] C_stk_delta;
  reg C_stk_write;
  wire [7:0] c_stk_w = T=="~" ? tc_plus_1 : T=="{" ? tc : A[7:0];
  wire [7:0] c_stk_r;

  always @* begin
    case({stall, |depth, T})
      {2'b0_0, "?"}    : {C_stk_write, C_stk_delta} = {1'b0, 2'b11}; //pop (return)
      {2'b0_0, ")"}    : {C_stk_write, C_stk_delta} = {1'b0, 2'b11}; //pop (return)
      {2'b0_0, "}"}    : {C_stk_write, C_stk_delta} = {1'b0, 2'b11}; //pop (return)
      {2'b0_0, "~"}    : {C_stk_write, C_stk_delta} = {1'b1, 2'b01}; //push (call)
      {2'b0_0, "{"}    : {C_stk_write, C_stk_delta} = {1'b1, 2'b01}; //push (call)
      default          : {C_stk_write, C_stk_delta} = {1'b0, 2'b00}; //hold
      endcase
    end 

  // table
  reg [`TABLE_WIDTH-1:0] idx, idx_;
  reg search_clk; 
  reg stall, stall_;

  wire table_search = (T=="!" | T=="@" | T=="~" | T=="(")  ? 1'b1 : 1'b0; 
  wire table_write = (T=="!" | T=="(") ? 1'b1 : 1'b0;
  wire [15:0] table_rd;
  wire [15:0] key_rd; 
  wire found_slot  = stall & (table_write ? (key_rd == A) | (key_rd == 0) 
                                           : (key_rd == A) & (key_rd != 0));

  wire write_slot = (table_write && found_slot && stall) ? 1'b1 : 1'b0;
  wire [15:0] table_wr_data = T == "(" ? tc_plus_1 : S;

  always @* begin
    casez({search_clk, found_slot, table_search, uart_stall, stall})
      5'b?_?_1_0_0: {stall_, idx_} = {1'b1, A[`TABLE_WIDTH-1:0]}; //table stall
      5'b1_0_1_0_1: {stall_, idx_} = {stall, idx + 1'b1};         //table clash, inc
      5'b1_1_1_0_1: {stall_, idx_} = {1'b0, idx};                 //table un-stall      
      5'b?_?_?_1_0: {stall_, idx_} = {1'b1, idx};                 //uart stall
      5'b?_?_?_0_1: {stall_, idx_} = {1'b0, idx};                 //uart un-stall      
      default:      {stall_, idx_} = {stall, idx};                //no change
      endcase
    end        

  // core
  reg [7:0] tc, tc_;
  wire [7:0] tc_plus_1 = tc + 1'b1;
  reg [15:0] A, A_;    

  // A
  always @* begin
    if(depth==0 & T=="(") A_ = S;
    else if(stall | depth_) A_ = A; 
    else begin
      case(T)
        "0","1","2","3","4","5","6","7","8","9" : A_ = (A << 4) | (T - "0");
        "A","B","C","D","E","F" : A_ = (A << 4) | (T - "7");
        "a","b","c","d","e","f","g","h","i","j","k","l","m"
        ,"n","o","p","q","r","s","t","u","v","w","x","y","z" : A_ = ((A<<5)^16'h1505)^T;
        " " : A_ = 16'h0; 
        "+" : A_ = A + S;
        "-" : A_ = S - A;
        "_" : A_ = ~A;
        "=" : A_ = A == S ? -1'b1 : 1'b0;
        "!", "%", "~" : A_ = S;
        "#" : A_ = S + 1'b1;
        "@" : A_ = table_rd;
        "'" : A_ = A << 8 | uart_rx_data;
        "\"": A_ = A >> 8;
        default: A_ = A;
      endcase
    end  
  end

  // depth
  reg [3:0] depth, depth_;
  always @* begin
    case({stall, |depth, T})
      {2'b0_0,"("}     : depth_ = depth+1'b1;
      {2'b0_1,")"}     : depth_ = depth-1'b1;
      default          : depth_ = depth;
      endcase
    end  

  // tc
  always @* begin
    casez({stall_, depth, T})
      13'b1_????_????????  : tc_ <= tc; 
      {1'b0, 4'h0, "~"}    : tc_ <= table_rd[7:0];
      {1'b0, 4'h0, ")"}    : tc_ <= c_stk_r;  
      {1'b0, 4'h0, "}"}    : tc_ <= c_stk_r; 
      {1'b0, 4'h0, "?"}    : tc_ <= A ? c_stk_r : tc_plus_1;      
      default              : tc_ <= tc_plus_1;    
      endcase 
    end


  // clk  
  always @(posedge clk or negedge reset) begin
    if (!reset) begin
      A <= 0;
      tc <= -1; 
      search_clk <= 0;
      depth <= 0;
      stall <= 0;
      idx <= 0;
      end
    else begin
      A <= A_;
      tc <= tc_; 
      depth <= depth_;
      search_clk <= ~search_clk;
      stall <= stall_;
      idx <= idx_;
      end
    end    


RAM ram(
.din(A_low),
.write_en(write_flag),
.waddr(S[`RAM_WIDTH-1:0]),
.wclk(clk),
.raddr(tc_),
.rclk(clk),
.dout(T)
);
defparam ram.addr_width = 8;
defparam ram.data_width = 8;
defparam ram.init_file = "init.hex";

STACK A_stk(
.clk(clk),
.rd(S),
.wd(A),
.we(A_stk_write),
.delta(A_stk_delta)
);
defparam A_stk.DEPTH = 8;
defparam A_stk.WIDTH = 16;

STACK C_stk(
.clk(clk),
.rd(c_stk_r),
.wd(c_stk_w),
.we(C_stk_write),
.delta(C_stk_delta)
);
defparam C_stk.DEPTH = 8;
defparam C_stk.WIDTH = 8;

RAM keys(
.din(A),
.write_en(write_slot),
.waddr(idx),
.wclk(clk),
.raddr(idx),
.rclk(clk),
.dout(key_rd)
);
defparam keys.addr_width = `TABLE_WIDTH;
defparam keys.data_width = 16;
defparam keys.init_file = "blank256.hex"; 

RAM vals(
.din(table_wr_data),
.write_en(write_slot),
.waddr(idx),
.wclk(clk),
.raddr(idx),
.rclk(clk),
.dout(table_rd)
);
defparam vals.addr_width = `TABLE_WIDTH;
defparam vals.data_width = 16;
defparam vals.init_file = "blank256.hex"; 

UART uart(
.clk(clk),
.resetq(reset),
.rx(rx),
.tx(tx),
.rd(uart_rd), 
.wr(uart_wr),
.valid(uart_rx_valid),
.busy(uart_tx_busy),
.tx_data(A_[7:0]),
.rx_data(uart_rx_data),
.error(uart_error)
);



endmodule

test.v
`timescale 1 ns / 1 ns

module test;

  /* Make a reset that pulses once. */
  reg reset = 0;
  initial begin
     $dumpfile("wave.vcd");
     $dumpvars(0,test);

     # 1  reset = 1;
     # 512 $finish;
  end

  /* Make a regular pulsing clock. */
  reg clk = 0;
  always #1 clk = !clk;

  wire tx, rx;
  TOK tok(clk, reset, tx, rx);

endmodule // test

wave.vcd
$date
	Thu Dec 31 10:39:02 2020
$end
$version
	Icarus Verilog
$end
$timescale
	1ns
$end
$scope module test $end
$var wire 1 ! rx $end
$var wire 1 " tx $end
$var reg 1 # clk $end
$var reg 1 $ reset $end
$scope module tok $end
$var wire 1 # clk $end
$var wire 1 % found_slot $end
$var wire 1 $ reset $end
$var wire 1 ! rx $end
$var wire 1 & uart_rd $end
$var wire 1 ' uart_stall $end
$var wire 1 ( uart_wr $end
$var wire 1 ) write_slot $end
$var wire 1 * write_flag $end
$var wire 1 + uart_tx_busy $end
$var wire 1 , uart_rx_valid $end
$var wire 8 - uart_rx_data [7:0] $end
$var wire 1 . uart_error $end
$var wire 1 " tx $end
$var wire 8 / tc_plus_1 [7:0] $end
$var wire 1 0 table_write $end
$var wire 16 1 table_wr_data [15:0] $end
$var wire 1 2 table_search $end
$var wire 16 3 table_rd [15:0] $end
$var wire 16 4 key_rd [15:0] $end
$var wire 8 5 c_stk_w [7:0] $end
$var wire 8 6 c_stk_r [7:0] $end
$var wire 8 7 T [7:0] $end
$var wire 16 8 S [15:0] $end
$var wire 8 9 A_low [7:0] $end
$var reg 16 : A [15:0] $end
$var reg 16 ; A_ [15:0] $end
$var reg 2 < A_stk_delta [1:0] $end
$var reg 1 = A_stk_write $end
$var reg 2 > C_stk_delta [1:0] $end
$var reg 1 ? C_stk_write $end
$var reg 4 @ depth [3:0] $end
$var reg 4 A depth_ [3:0] $end
$var reg 8 B idx [7:0] $end
$var reg 8 C idx_ [7:0] $end
$var reg 1 D search_clk $end
$var reg 1 E stall $end
$var reg 1 F stall_ $end
$var reg 8 G tc [7:0] $end
$var reg 8 H tc_ [7:0] $end
$scope module A_stk $end
$var wire 1 # clk $end
$var wire 2 I delta [1:0] $end
$var wire 16 J rd [15:0] $end
$var wire 16 K wd [15:0] $end
$var wire 1 = we $end
$var wire 128 L tailN [127:0] $end
$var wire 1 M move $end
$var wire 16 N headN [15:0] $end
$var reg 16 O head [15:0] $end
$var reg 128 P tail [127:0] $end
$upscope $end
$scope module C_stk $end
$var wire 1 # clk $end
$var wire 2 Q delta [1:0] $end
$var wire 8 R rd [7:0] $end
$var wire 8 S wd [7:0] $end
$var wire 1 ? we $end
$var wire 64 T tailN [63:0] $end
$var wire 1 U move $end
$var wire 8 V headN [7:0] $end
$var reg 8 W head [7:0] $end
$var reg 64 X tail [63:0] $end
$upscope $end
$scope module keys $end
$var wire 16 Y din [15:0] $end
$var wire 8 Z raddr [7:0] $end
$var wire 1 # rclk $end
$var wire 8 [ waddr [7:0] $end
$var wire 1 # wclk $end
$var wire 1 ) write_en $end
$var reg 16 \ dout [15:0] $end
$upscope $end
$scope module ram $end
$var wire 8 ] din [7:0] $end
$var wire 8 ^ raddr [7:0] $end
$var wire 1 # rclk $end
$var wire 8 _ waddr [7:0] $end
$var wire 1 # wclk $end
$var wire 1 * write_en $end
$var reg 8 ` dout [7:0] $end
$upscope $end
$scope module uart $end
$var wire 1 + busy $end
$var wire 1 # clk $end
$var wire 1 a good $end
$var wire 1 b nonstarter $end
$var wire 1 & rd $end
$var wire 1 $ resetq $end
$var wire 1 ! rx $end
$var wire 1 c rxrst $end
$var wire 1 d sample $end
$var wire 8 e tx_data [7:0] $end
$var wire 1 ( wr $end
$var wire 1 f txtick $end
$var wire 1 " tx $end
$var wire 1 g stopbit $end
$var wire 1 h startbit $end
$var wire 1 i rxstop $end
$var wire 1 j rxqtick $end
$var wire 1 k done $end
$var reg 6 l bytephase [5:0] $end
$var reg 10 m capture [9:0] $end
$var reg 1 . error $end
$var reg 8 n rx_data [7:0] $end
$var reg 7 o rxclkcounter [6:0] $end
$var reg 10 p sender [9:0] $end
$var reg 4 q sentbits [3:0] $end
$var reg 9 r txclkcounter [8:0] $end
$var reg 1 , valid $end
$upscope $end
$scope module vals $end
$var wire 16 s din [15:0] $end
$var wire 8 t raddr [7:0] $end
$var wire 1 # rclk $end
$var wire 8 u waddr [7:0] $end
$var wire 1 # wclk $end
$var wire 1 ) write_en $end
$var reg 16 v dout [15:0] $end
$upscope $end
$upscope $end
$upscope $end
$enddefinitions $end
#0
$dumpvars
bx v
b0 u
b0 t
bx s
bx r
bx q
bx p
bx o
bx n
bx m
bx l
xk
xj
xi
xh
xg
xf
b100101 e
xd
xc
xb
xa
bx `
bx _
b0 ^
b0 ]
bx \
b0 [
b0 Z
b0 Y
bx X
bx W
bx V
0U
bx T
bx S
bx R
b0 Q
bx P
bx O
bx N
0M
bx L
b0 K
bx J
b0 I
b0 H
b11111111 G
0F
0E
0D
b0 C
b0 B
b0 A
b0 @
0?
b0 >
0=
b0 <
b0 ;
b0 :
b0 9
bx 8
bx 7
bx 6
bx 5
bx 4
bx 3
x2
bx 1
x0
b0 /
x.
bx -
x,
x+
x*
0)
x(
x'
x&
0%
0$
0#
x"
z!
$end
#1
b1 H
b1 ^
00
02
0'
b0 5
b0 S
0(
0&
b10 ;
0*
b110010 7
b110010 `
b0 4
b0 \
b0 3
b0 v
1D
b1 /
b0 G
1#
1$
#2
0#
#3
b10 H
b10 ^
b10 5
b10 S
b10 9
b10 ]
b100101 ;
b110101 7
b110101 `
0D
b10 /
b1 G
b10 :
b10 K
b10 Y
1#
#4
0#
#5
b11 H
b11 ^
b100101 5
b100101 S
x'
x(
b100101 9
b100101 ]
b0 ;
b100010 7
b100010 `
1D
b11 /
b10 G
b100101 :
b100101 K
b100101 Y
1#
#6
0#
#7
b100 H
b100 ^
b0 5
b0 S
0'
b0 N
1M
0(
1=
b1 <
b1 I
b0 9
b0 ]
b100000 7
b100000 `
0D
b100 /
b11 G
b0 :
b0 K
b0 Y
1#
#8
0#
#9
b101 H
b101 ^
bx N
0M
0=
b0 <
b0 I
bx0000000000000000 L
b0 _
b0 1
b0 s
b10 ;
b110010 7
b110010 `
b0 8
b0 J
b0 O
1D
b101 /
b100 G
1#
#10
0#
#11
b110 H
b110 ^
b10 5
b10 S
b10 9
b10 ]
b100110 ;
b110110 7
b110110 `
0D
b110 /
b101 G
b10 :
b10 K
b10 Y
1#
#12
0#
#13
b111 H
b111 ^
b100110 5
b100110 S
x'
x(
b100110 9
b100110 ]
b0 ;
b100010 7
b100010 `
1D
b111 /
b110 G
b100110 :
b100110 K
b100110 Y
1#
#14
0#
#15
b1000 H
b1000 ^
b0 5
b0 S
0'
b0 N
1M
0(
1=
b1 <
b1 I
b0 9
b0 ]
b100000 7
b100000 `
0D
b1000 /
b111 G
b0 :
b0 K
b0 Y
1#
#16
0#
#17
b1001 H
b1001 ^
0M
bx00000000000000000000000000000000 L
b10 ;
0=
b0 <
b0 I
b110010 7
b110010 `
bx0000000000000000 P
1D
b1001 /
b1000 G
1#
#18
0#
#19
b1010 H
b1010 ^
b10 5
b10 S
b10 9
b10 ]
b100111 ;
b110111 7
b110111 `
0D
b1010 /
b1001 G
b10 :
b10 K
b10 Y
1#
#20
0#
#21
b1011 H
b1011 ^
b100111 5
b100111 S
x'
x(
b100111 9
b100111 ]
b0 ;
b100010 7
b100010 `
1D
b1011 /
b1010 G
b100111 :
b100111 K
b100111 Y
1#
#22
0#
#23
b1100 H
b1100 ^
b0 5
b0 S
0'
1M
0(
1=
b1 <
b1 I
b0 9
b0 ]
b100000 7
b100000 `
0D
b1100 /
b1011 G
b0 :
b0 K
b0 Y
1#
#24
0#
#25
b1101 H
b1101 ^
0M
bx000000000000000000000000000000000000000000000000 L
b10 ;
0=
b0 <
b0 I
b110010 7
b110010 `
bx00000000000000000000000000000000 P
1D
b1101 /
b1100 G
1#
#26
0#
#27
b1110 H
b1110 ^
b10 5
b10 S
b10 9
b10 ]
b101000 ;
b111000 7
b111000 `
0D
b1110 /
b1101 G
b10 :
b10 K
b10 Y
1#
#28
0#
#29
b1111 H
b1111 ^
b101000 5
b101000 S
x'
x(
b101000 9
b101000 ]
b0 ;
b100010 7
b100010 `
1D
b1111 /
b1110 G
b101000 :
b101000 K
b101000 Y
1#
#30
0#
#31
b10000 H
b10000 ^
b0 5
b0 S
0'
0(
b0 9
b0 ]
b0 7
b0 `
0D
b10000 /
b1111 G
b0 :
b0 K
b0 Y
1#
#32
0#
#33
b10001 H
b10001 ^
1D
b10001 /
b10000 G
1#
#34
0#
#35
b10010 H
b10010 ^
0D
b10010 /
b10001 G
1#
#36
0#
#37
b10011 H
b10011 ^
1D
b10011 /
b10010 G
1#
#38
0#
#39
b10100 H
b10100 ^
0D
b10100 /
b10011 G
1#
#40
0#
#41
b10101 H
b10101 ^
1D
b10101 /
b10100 G
1#
#42
0#
#43
b10110 H
b10110 ^
0D
b10110 /
b10101 G
1#
#44
0#
#45
b10111 H
b10111 ^
1D
b10111 /
b10110 G
1#
#46
0#
#47
b11000 H
b11000 ^
0D
b11000 /
b10111 G
1#
#48
0#
#49
b11001 H
b11001 ^
1D
b11001 /
b11000 G
1#
#50
0#
#51
b11010 H
b11010 ^
0D
b11010 /
b11001 G
1#
#52
0#
#53
b11011 H
b11011 ^
1D
b11011 /
b11010 G
1#
#54
0#
#55
b11100 H
b11100 ^
0D
b11100 /
b11011 G
1#
#56
0#
#57
b11101 H
b11101 ^
1D
b11101 /
b11100 G
1#
#58
0#
#59
b11110 H
b11110 ^
0D
b11110 /
b11101 G
1#
#60
0#
#61
b11111 H
b11111 ^
1D
b11111 /
b11110 G
1#
#62
0#
#63
b100000 H
b100000 ^
0D
b100000 /
b11111 G
1#
#64
0#
#65
b100001 H
b100001 ^
1D
b100001 /
b100000 G
1#
#66
0#
#67
b100010 H
b100010 ^
0D
b100010 /
b100001 G
1#
#68
0#
#69
b100011 H
b100011 ^
1D
b100011 /
b100010 G
1#
#70
0#
#71
b100100 H
b100100 ^
0D
b100100 /
b100011 G
1#
#72
0#
#73
b100101 H
b100101 ^
1D
b100101 /
b100100 G
1#
#74
0#
#75
b100110 H
b100110 ^
0D
b100110 /
b100101 G
1#
#76
0#
#77
b100111 H
b100111 ^
1D
b100111 /
b100110 G
1#
#78
0#
#79
b101000 H
b101000 ^
0D
b101000 /
b100111 G
1#
#80
0#
#81
b101001 H
b101001 ^
1D
b101001 /
b101000 G
1#
#82
0#
#83
b101010 H
b101010 ^
0D
b101010 /
b101001 G
1#
#84
0#
#85
b101011 H
b101011 ^
1D
b101011 /
b101010 G
1#
#86
0#
#87
b101100 H
b101100 ^
0D
b101100 /
b101011 G
1#
#88
0#
#89
b101101 H
b101101 ^
1D
b101101 /
b101100 G
1#
#90
0#
#91
b101110 H
b101110 ^
0D
b101110 /
b101101 G
1#
#92
0#
#93
b101111 H
b101111 ^
1D
b101111 /
b101110 G
1#
#94
0#
#95
b110000 H
b110000 ^
0D
b110000 /
b101111 G
1#
#96
0#
#97
b110001 H
b110001 ^
1D
b110001 /
b110000 G
1#
#98
0#
#99
b110010 H
b110010 ^
0D
b110010 /
b110001 G
1#
#100
0#
#101
b110011 H
b110011 ^
1D
b110011 /
b110010 G
1#
#102
0#
#103
b110100 H
b110100 ^
0D
b110100 /
b110011 G
1#
#104
0#
#105
b110101 H
b110101 ^
1D
b110101 /
b110100 G
1#
#106
0#
#107
b110110 H
b110110 ^
0D
b110110 /
b110101 G
1#
#108
0#
#109
b110111 H
b110111 ^
1D
b110111 /
b110110 G
1#
#110
0#
#111
b111000 H
b111000 ^
0D
b111000 /
b110111 G
1#
#112
0#
#113
b111001 H
b111001 ^
1D
b111001 /
b111000 G
1#
#114
0#
#115
b111010 H
b111010 ^
0D
b111010 /
b111001 G
1#
#116
0#
#117
b111011 H
b111011 ^
1D
b111011 /
b111010 G
1#
#118
0#
#119
b111100 H
b111100 ^
0D
b111100 /
b111011 G
1#
#120
0#
#121
b111101 H
b111101 ^
1D
b111101 /
b111100 G
1#
#122
0#
#123
b111110 H
b111110 ^
0D
b111110 /
b111101 G
1#
#124
0#
#125
b111111 H
b111111 ^
1D
b111111 /
b111110 G
1#
#126
0#
#127
b1000000 H
b1000000 ^
0D
b1000000 /
b111111 G
1#
#128
0#
#129
b1000001 H
b1000001 ^
1D
b1000001 /
b1000000 G
1#
#130
0#
#131
b1000010 H
b1000010 ^
0D
b1000010 /
b1000001 G
1#
#132
0#
#133
b1000011 H
b1000011 ^
1D
b1000011 /
b1000010 G
1#
#134
0#
#135
b1000100 H
b1000100 ^
0D
b1000100 /
b1000011 G
1#
#136
0#
#137
b1000101 H
b1000101 ^
1D
b1000101 /
b1000100 G
1#
#138
0#
#139
b1000110 H
b1000110 ^
0D
b1000110 /
b1000101 G
1#
#140
0#
#141
b1000111 H
b1000111 ^
1D
b1000111 /
b1000110 G
1#
#142
0#
#143
b1001000 H
b1001000 ^
0D
b1001000 /
b1000111 G
1#
#144
0#
#145
b1001001 H
b1001001 ^
1D
b1001001 /
b1001000 G
1#
#146
0#
#147
b1001010 H
b1001010 ^
0D
b1001010 /
b1001001 G
1#
#148
0#
#149
b1001011 H
b1001011 ^
1D
b1001011 /
b1001010 G
1#
#150
0#
#151
b1001100 H
b1001100 ^
0D
b1001100 /
b1001011 G
1#
#152
0#
#153
b1001101 H
b1001101 ^
1D
b1001101 /
b1001100 G
1#
#154
0#
#155
b1001110 H
b1001110 ^
0D
b1001110 /
b1001101 G
1#
#156
0#
#157
b1001111 H
b1001111 ^
1D
b1001111 /
b1001110 G
1#
#158
0#
#159
b1010000 H
b1010000 ^
0D
b1010000 /
b1001111 G
1#
#160
0#
#161
b1010001 H
b1010001 ^
1D
b1010001 /
b1010000 G
1#
#162
0#
#163
b1010010 H
b1010010 ^
0D
b1010010 /
b1010001 G
1#
#164
0#
#165
b1010011 H
b1010011 ^
1D
b1010011 /
b1010010 G
1#
#166
0#
#167
b1010100 H
b1010100 ^
0D
b1010100 /
b1010011 G
1#
#168
0#
#169
b1010101 H
b1010101 ^
1D
b1010101 /
b1010100 G
1#
#170
0#
#171
b1010110 H
b1010110 ^
0D
b1010110 /
b1010101 G
1#
#172
0#
#173
b1010111 H
b1010111 ^
1D
b1010111 /
b1010110 G
1#
#174
0#
#175
b1011000 H
b1011000 ^
0D
b1011000 /
b1010111 G
1#
#176
0#
#177
b1011001 H
b1011001 ^
1D
b1011001 /
b1011000 G
1#
#178
0#
#179
b1011010 H
b1011010 ^
0D
b1011010 /
b1011001 G
1#
#180
0#
#181
b1011011 H
b1011011 ^
1D
b1011011 /
b1011010 G
1#
#182
0#
#183
b1011100 H
b1011100 ^
0D
b1011100 /
b1011011 G
1#
#184
0#
#185
b1011101 H
b1011101 ^
1D
b1011101 /
b1011100 G
1#
#186
0#
#187
b1011110 H
b1011110 ^
0D
b1011110 /
b1011101 G
1#
#188
0#
#189
b1011111 H
b1011111 ^
1D
b1011111 /
b1011110 G
1#
#190
0#
#191
b1100000 H
b1100000 ^
0D
b1100000 /
b1011111 G
1#
#192
0#
#193
b1100001 H
b1100001 ^
1D
b1100001 /
b1100000 G
1#
#194
0#
#195
b1100010 H
b1100010 ^
0D
b1100010 /
b1100001 G
1#
#196
0#
#197
b1100011 H
b1100011 ^
1D
b1100011 /
b1100010 G
1#
#198
0#
#199
b1100100 H
b1100100 ^
0D
b1100100 /
b1100011 G
1#
#200
0#
#201
b1100101 H
b1100101 ^
1D
b1100101 /
b1100100 G
1#
#202
0#
#203
b1100110 H
b1100110 ^
0D
b1100110 /
b1100101 G
1#
#204
0#
#205
b1100111 H
b1100111 ^
1D
b1100111 /
b1100110 G
1#
#206
0#
#207
b1101000 H
b1101000 ^
0D
b1101000 /
b1100111 G
1#
#208
0#
#209
b1101001 H
b1101001 ^
1D
b1101001 /
b1101000 G
1#
#210
0#
#211
b1101010 H
b1101010 ^
0D
b1101010 /
b1101001 G
1#
#212
0#
#213
b1101011 H
b1101011 ^
1D
b1101011 /
b1101010 G
1#
#214
0#
#215
b1101100 H
b1101100 ^
0D
b1101100 /
b1101011 G
1#
#216
0#
#217
b1101101 H
b1101101 ^
1D
b1101101 /
b1101100 G
1#
#218
0#
#219
b1101110 H
b1101110 ^
0D
b1101110 /
b1101101 G
1#
#220
0#
#221
b1101111 H
b1101111 ^
1D
b1101111 /
b1101110 G
1#
#222
0#
#223
b1110000 H
b1110000 ^
0D
b1110000 /
b1101111 G
1#
#224
0#
#225
b1110001 H
b1110001 ^
1D
b1110001 /
b1110000 G
1#
#226
0#
#227
b1110010 H
b1110010 ^
0D
b1110010 /
b1110001 G
1#
#228
0#
#229
b1110011 H
b1110011 ^
1D
b1110011 /
b1110010 G
1#
#230
0#
#231
b1110100 H
b1110100 ^
0D
b1110100 /
b1110011 G
1#
#232
0#
#233
b1110101 H
b1110101 ^
1D
b1110101 /
b1110100 G
1#
#234
0#
#235
b1110110 H
b1110110 ^
0D
b1110110 /
b1110101 G
1#
#236
0#
#237
b1110111 H
b1110111 ^
1D
b1110111 /
b1110110 G
1#
#238
0#
#239
b1111000 H
b1111000 ^
0D
b1111000 /
b1110111 G
1#
#240
0#
#241
b1111001 H
b1111001 ^
1D
b1111001 /
b1111000 G
1#
#242
0#
#243
b1111010 H
b1111010 ^
0D
b1111010 /
b1111001 G
1#
#244
0#
#245
b1111011 H
b1111011 ^
1D
b1111011 /
b1111010 G
1#
#246
0#
#247
b1111100 H
b1111100 ^
0D
b1111100 /
b1111011 G
1#
